pcreode/__init__.py
pcreode/functions.py
pcreode/pcreode.py
pcreode-2.2.2.dist-info/LICENSE
pcreode-2.2.2.dist-info/METADATA
pcreode-2.2.2.dist-info/WHEEL
pcreode-2.2.2.dist-info/top_level.txt
pcreode-2.2.2.dist-info/RECORD
