Metadata-Version: 2.1
Name: pcreode
Version: 2.2.2
Summary: p-Creode algorithm for mapping state transitions
Home-page: https://github.com/KenLauLab/pCreode
Author: Chuck Herring
Author-email: charles.a.herring@Vanderbilt.edu
License-File: LICENSE
Requires-Dist: numpy (>=1.11.0)
Requires-Dist: pandas (>=0.17.1)
Requires-Dist: python-igraph (<=0.9.11)
Requires-Dist: matplotlib
Requires-Dist: sklearn
Requires-Dist: jgraph
Requires-Dist: jupyter
Requires-Dist: nvr
Requires-Dist: cairocffi
